odoo/addons/l10n_es_facturae/README.rst
odoo/addons/l10n_es_facturae/__init__.py
odoo/addons/l10n_es_facturae/__manifest__.py
odoo/addons/l10n_es_facturae/data/Facturaev3_2.xsd
odoo/addons/l10n_es_facturae/data/Facturaev3_2_1.xsd
odoo/addons/l10n_es_facturae/data/Facturaev3_2_2.xsd
odoo/addons/l10n_es_facturae/data/account_tax_template.xml
odoo/addons/l10n_es_facturae/data/xmldsig-core-schema.xsd
odoo/addons/l10n_es_facturae/i18n/bg.po
odoo/addons/l10n_es_facturae/i18n/ca.po
odoo/addons/l10n_es_facturae/i18n/cs.po
odoo/addons/l10n_es_facturae/i18n/de.po
odoo/addons/l10n_es_facturae/i18n/es.po
odoo/addons/l10n_es_facturae/i18n/es_CO.po
odoo/addons/l10n_es_facturae/i18n/es_CR.po
odoo/addons/l10n_es_facturae/i18n/es_ES.po
odoo/addons/l10n_es_facturae/i18n/eu.po
odoo/addons/l10n_es_facturae/i18n/fr.po
odoo/addons/l10n_es_facturae/i18n/gl.po
odoo/addons/l10n_es_facturae/i18n/hr.po
odoo/addons/l10n_es_facturae/i18n/l10n_es_facturae.pot
odoo/addons/l10n_es_facturae/i18n/nl.po
odoo/addons/l10n_es_facturae/i18n/pl.po
odoo/addons/l10n_es_facturae/i18n/pt.po
odoo/addons/l10n_es_facturae/i18n/pt_BR.po
odoo/addons/l10n_es_facturae/i18n/ru.po
odoo/addons/l10n_es_facturae/i18n/sl.po
odoo/addons/l10n_es_facturae/i18n/sv.po
odoo/addons/l10n_es_facturae/i18n/tr.po
odoo/addons/l10n_es_facturae/i18n/vi.po
odoo/addons/l10n_es_facturae/migrations/13.0.1.0.0/post-migration.py
odoo/addons/l10n_es_facturae/migrations/13.0.1.0.0/pre-migration.py
odoo/addons/l10n_es_facturae/migrations/13.0.1.0.1/pre-migration.py
odoo/addons/l10n_es_facturae/migrations/13.0.2.0.0/pre-migration.py
odoo/addons/l10n_es_facturae/models/__init__.py
odoo/addons/l10n_es_facturae/models/account_move.py
odoo/addons/l10n_es_facturae/models/account_tax.py
odoo/addons/l10n_es_facturae/models/account_tax_template.py
odoo/addons/l10n_es_facturae/models/payment_mode.py
odoo/addons/l10n_es_facturae/models/res_company.py
odoo/addons/l10n_es_facturae/models/res_currency.py
odoo/addons/l10n_es_facturae/models/res_partner.py
odoo13_addon_l10n_es_facturae-13.0.2.5.1.dist-info/METADATA
odoo13_addon_l10n_es_facturae-13.0.2.5.1.dist-info/WHEEL
odoo13_addon_l10n_es_facturae-13.0.2.5.1.dist-info/top_level.txt
odoo13_addon_l10n_es_facturae-13.0.2.5.1.dist-info/RECORD
