Metadata-Version: 2.1
Name: odoo13-addon-l10n-es-facturae
Version: 13.0.2.5.1
Summary: Creación de Factura-e
Home-page: https://github.com/OCA/l10n-spain
Author: ASR-OSS, FactorLibre, Tecon, Comunitea, Tecnativa, Creu Blanca, Odoo Community Association (OCA)
Author-email: support@odoo-community.org
License: AGPL-3
Platform: UNKNOWN
Classifier: Programming Language :: Python
Classifier: Framework :: Odoo
Classifier: Framework :: Odoo :: 13.0
Classifier: License :: OSI Approved :: GNU Affero General Public License v3
Requires-Python: >=3.5
Requires-Dist: odoo13-addon-account-payment-partner
Requires-Dist: odoo13-addon-base-iso3166
Requires-Dist: odoo13-addon-l10n-es-aeat
Requires-Dist: odoo13-addon-l10n-es-partner
Requires-Dist: odoo13-addon-report-qweb-parameter
Requires-Dist: odoo13-addon-report-xml
Requires-Dist: odoo <13.1dev,>=13.0a
Requires-Dist: pyOpenSSL
Requires-Dist: xmlsig
